djangorestframework_api_gateway_auth/__init__.py
djangorestframework_api_gateway_auth/authentication.py
djangorestframework_api_gateway_auth-0.2.0.dist-info/WHEEL
djangorestframework_api_gateway_auth-0.2.0.dist-info/METADATA
djangorestframework_api_gateway_auth-0.2.0.dist-info/RECORD
